{
    "name": "High Fidelity",
    "name-key": "high-fidelity-01",
    "name-key-sub": "",
    "name-key-canonical": "",
    "type": "serial",
    "id": "1",

    "id-imdb": "https://www.imdb.com/title/tt8577458",
    "id-wikipedia": "https://en.wikipedia.org/wiki/High_Fidelity_(TV_series)",

    "genre-tags": ["romantic comedy", "drama", "romance", "diverse ensemble"],
    "bias-tags": [""],

    "plot-tags": ["remake", "adaptation", "record store", "music", "past relationships", "true love"],
    "plot-geo": ["usa", "new york", "brooklyn", "crown heights"],
    "plot-date": ["2010s"],

    "distribution-tags": ["hulu", "disney-abc domestic television"],
    "production-tags": ["west & kucserka", "midnight radio", "abc signature studios"],
    "production-geo": ["usa", "new york city"],

    "reception-positive": [""],
    "reception-negative": [""],

    "cast-lead-1-ethnicities": ["black", "multi"],
    "cast-lead-1-nationalities": ["usa"],
    "cast-lead-1-genders": ["cis", "female"],
    "cast-lead-1-sexualities": ["bisexual"],
    "cast-lead-1-ages": ["20-29", "30-39", "30-39 playing 20-29"],
    "cast-lead-1-z": ["human"],
    "cast-lead-1-names": [""],

    "cast-lead-2-ethnicities": ["white"],
    "cast-lead-2-nationalities": ["usa"],
    "cast-lead-2-genders": ["cis", "male"],
    "cast-lead-2-sexualities": ["straight"],
    "cast-lead-2-ages": ["30-39"],
    "cast-lead-2-z": ["human"],
    "cast-lead-2-names": [""],

    "cast-lead-3-ethnicities": ["black"],
    "cast-lead-3-nationalities": ["usa"],
    "cast-lead-3-genders": ["cis", "female"],
    "cast-lead-3-sexualities": ["straight"],
    "cast-lead-3-ages": ["30-39"],
    "cast-lead-3-z": ["human"],
    "cast-lead-3-names": [""],

    "cast-lead-4-ethnicities": ["white"],
    "cast-lead-4-nationalities": ["usa"],
    "cast-lead-4-genders": ["cis", "male"],
    "cast-lead-4-sexualities": ["gay", "unknown", "unknown playing gay"],
    "cast-lead-4-ages": ["30-39"],
    "cast-lead-4-z": ["human"],
    "cast-lead-4-names": [""],

    "cast-lead-5-ethnicities": ["black"],
    "cast-lead-5-nationalities": ["usa", "gbr", "gbr playing usa"],
    "cast-lead-5-genders": ["cis", "male"],
    "cast-lead-5-sexualities": ["straight"],
    "cast-lead-5-ages": ["30-39"],
    "cast-lead-5-z": ["human"],
    "cast-lead-5-names": [""],

    "cast-lead-6-ethnicities": ["black", "multi"],
    "cast-lead-6-nationalities": ["usa", "can", "can playing usa"],
    "cast-lead-6-genders": ["male", "cis"],
    "cast-lead-6-sexualities": ["straight"],
    "cast-lead-6-ages": ["40-49", "40-49 playing unknown"],
    "cast-lead-6-z": ["human"],
    "cast-lead-6-names": [""],

    "cast-lead-7-ethnicities": [""],
    "cast-lead-7-nationalities": [""],
    "cast-lead-7-genders": [""],
    "cast-lead-7-sexualities": [""],
    "cast-lead-7-ages": [""],
    "cast-lead-7-z": [""],
    "cast-lead-7-names": [""],

    "cast-lead-8-ethnicities": [""],
    "cast-lead-8-nationalities": [""],
    "cast-lead-8-genders": [""],
    "cast-lead-8-sexualities": [""],
    "cast-lead-8-ages": [""],
    "cast-lead-8-z": [""],
    "cast-lead-8-names": [""],

    "notes": ["rob, clyde, cherise, simon, mac, cameron"],

    "data-version": "20210317"
}
