{
    "name": "The Marvelous Mrs. Maisel",
    "name-key": "marvelous-mrs-maisel-03",
    "name-key-sub": "",
    "name-key-canonical": "",
    "type": "serial",
    "id": "3",

    "id-imdb": "https://www.imdb.com/title/tt5788792",
    "id-wikipedia": "https://en.wikipedia.org/wiki/The_Marvelous_Mrs._Maisel",

    "genre-tags": ["comedy", "drama", "period drama"],
    "bias-tags": [""],

    "plot-tags": ["stand up comedy", "working women", "jewish family"],
    "plot-geo": ["usa", "new york city"],
    "plot-date": ["1960"],

    "distribution-tags": ["amazon prime video"],
    "production-tags": ["dorothy parker drank here productions"],
    "production-geo": ["usa", "new york city"],

    "cast-lead-1-ethnicities": ["white"],
    "cast-lead-1-nationalities": ["usa"],
    "cast-lead-1-genders": ["cis", "female"],
    "cast-lead-1-sexualities": ["straight"],
    "cast-lead-1-ages": ["20-29"],
    "cast-lead-1-z": ["human"],
    "cast-lead-1-names": [""],

    "cast-lead-2-ethnicities": ["white"],
    "cast-lead-2-nationalities": ["usa"],
    "cast-lead-2-genders": ["cis", "female"],
    "cast-lead-2-sexualities": ["unknown"],
    "cast-lead-2-ages": ["40-49"],
    "cast-lead-2-z": ["human"],
    "cast-lead-2-names": [""],

    "cast-lead-3-ethnicities": ["white"],
    "cast-lead-3-nationalities": ["usa"],
    "cast-lead-3-genders": ["cis", "male"],
    "cast-lead-3-sexualities": ["straight"],
    "cast-lead-3-ages": ["20-29", "30-39", "30-39 playing 20-29"],
    "cast-lead-3-z": ["human"],
    "cast-lead-3-names": [""],

    "cast-lead-4-ethnicities": ["white"],
    "cast-lead-4-nationalities": ["usa"],
    "cast-lead-4-genders": ["cis", "male"],
    "cast-lead-4-sexualities": ["straight"],
    "cast-lead-4-ages": ["60-69"],
    "cast-lead-4-z": ["human"],
    "cast-lead-4-names": [""],

    "cast-lead-5-ethnicities": ["white"],
    "cast-lead-5-nationalities": ["usa"],
    "cast-lead-5-genders": ["cis", "female"],
    "cast-lead-5-sexualities": ["straight"],
    "cast-lead-5-ages": ["50-59"],
    "cast-lead-5-z": ["human"],
    "cast-lead-5-names": [""],

    "cast-lead-6-ethnicities": [""],
    "cast-lead-6-nationalities": [""],
    "cast-lead-6-genders": [""],
    "cast-lead-6-sexualities": [""],
    "cast-lead-6-ages": [""],
    "cast-lead-6-z": [""],
    "cast-lead-6-names": [""],

    "cast-lead-7-ethnicities": [""],
    "cast-lead-7-nationalities": [""],
    "cast-lead-7-genders": [""],
    "cast-lead-7-sexualities": [""],
    "cast-lead-7-ages": [""],
    "cast-lead-7-z": [""],
    "cast-lead-7-names": [""],

    "cast-lead-8-ethnicities": [""],
    "cast-lead-8-nationalities": [""],
    "cast-lead-8-genders": [""],
    "cast-lead-8-sexualities": [""],
    "cast-lead-8-ages": [""],
    "cast-lead-8-z": [""],
    "cast-lead-8-names": [""],

    "notes": ["midge, suzie, joel, abe, rose"],

    "data-version": "20210214"
}
